Metadata-Version: 2.1
Name: multilingual-translation
Version: 0.0.5
Summary: Multilingual Translation
Home-page: https://github.com/kadirnar/Multilingual-Translation
Author: kadirnar
License: MIT
Keywords: machine-learning,deep-learning,pytorch,nlp,natural-language-processing,translation,multilingual,multilingual-translation
Classifier: Development Status :: 5 - Production/Stable
Classifier: Operating System :: OS Independent
Classifier: Intended Audience :: Developers
Classifier: Intended Audience :: Science/Research
Classifier: Programming Language :: Python :: 3
Classifier: Programming Language :: Python :: 3.7
Classifier: Programming Language :: Python :: 3.8
Classifier: Programming Language :: Python :: 3.9
Classifier: Topic :: Software Development :: Libraries
Classifier: Topic :: Software Development :: Libraries :: Python Modules
Classifier: Topic :: Education
Classifier: Topic :: Scientific/Engineering
Classifier: Topic :: Scientific/Engineering :: Artificial Intelligence
Requires-Python: >=3.6
License-File: LICENSE
